CHANGES.rst
DESCRIPTION.rst
MANIFEST.in
README.md
setup.py
src/simple_redis_helper/__init__.py
src/simple_redis_helper/broadcast.py
src/simple_redis_helper/listen.py
src/simple_redis_helper/load.py
src/simple_redis_helper/ping.py
src/simple_redis_helper/save.py
src/simple_redis_helper/utils.py
src/simple_redis_helper.egg-info/PKG-INFO
src/simple_redis_helper.egg-info/SOURCES.txt
src/simple_redis_helper.egg-info/dependency_links.txt
src/simple_redis_helper.egg-info/entry_points.txt
src/simple_redis_helper.egg-info/requires.txt
src/simple_redis_helper.egg-info/top_level.txt