Metadata-Version: 1.1
Name: simple-redis-helper
Version: 0.1.6
Summary: Command-line utilities to for sending/receiving data to/from a Redis backend.
Home-page: https://github.com/fracpete/redis_helper
Author: Peter Reutemann
Author-email: fracpete@waikato.ac.nz
License: MIT License
Platform: UNKNOWN
Classifier: Development Status :: 4 - Beta
Classifier: License :: OSI Approved :: MIT License
Classifier: Topic :: Scientific/Engineering
Classifier: Programming Language :: Python :: 3
